sqlmelt/__init__.py
sqlmelt/melt.py
sqlmelt-0.1.0.dist-info/METADATA
sqlmelt-0.1.0.dist-info/WHEEL
sqlmelt-0.1.0.dist-info/licenses/LICENSE.txt
sqlmelt-0.1.0.dist-info/RECORD
