Metadata-Version: 2.4
Name: sqlmelt
Version: 0.1.0
Summary: This library is not that useful. Perhaps someday it will become great.
Author-email: ardavydovskiy <davydovskij.art@yandex.ru>
License-File: LICENSE.txt
Classifier: License :: OSI Approved :: MIT License
Classifier: Operating System :: OS Independent
Classifier: Programming Language :: Python :: 3
Requires-Python: >=3.0.0
